torchlambda/.dockerignore
torchlambda/CMakeLists.txt
torchlambda/Dockerfile
torchlambda/__init__.py
torchlambda/_version.py
torchlambda/build.sh
torchlambda/main.py
torchlambda/arguments/__init__.py
torchlambda/arguments/parser.py
torchlambda/arguments/subparsers.py
torchlambda/dependencies/aws-lambda.sh
torchlambda/dependencies/aws-sdk.sh
torchlambda/dependencies/torch.sh
torchlambda/implementation/__init__.py
torchlambda/implementation/build.py
torchlambda/implementation/docker.py
torchlambda/implementation/general.py
torchlambda/implementation/layer.py
torchlambda/implementation/template.py
torchlambda/implementation/utils/__init__.py
torchlambda/implementation/utils/template/__init__.py
torchlambda/implementation/utils/template/header.py
torchlambda/implementation/utils/template/imputation.py
torchlambda/implementation/utils/template/macro.py
torchlambda/implementation/utils/template/validator.py
torchlambda/subcommands/__init__.py
torchlambda/subcommands/build.py
torchlambda/subcommands/layer.py
torchlambda/subcommands/settings.py
torchlambda/subcommands/template.py
torchlambda/templates/custom/main.cpp
torchlambda/templates/settings/main.cpp
torchlambda/templates/settings/torchlambda.yaml
torchlambda-1602697918.dist-info/LICENSE
torchlambda-1602697918.dist-info/METADATA
torchlambda-1602697918.dist-info/WHEEL
torchlambda-1602697918.dist-info/entry_points.txt
torchlambda-1602697918.dist-info/top_level.txt
torchlambda-1602697918.dist-info/RECORD
