Metadata-Version: 2.1
Name: torchlambda
Version: 1602697918
Summary: Minimalistic & easy deployment of PyTorch models on AWS Lambda with C++
Home-page: https://github.com/pypa/torchlambda
Author: Szymon Maszke
Author-email: szymon.maszke@protonmail.com
License: MIT
Project-URL: Website, https://szymonmaszke.github.io/torchlambda
Project-URL: Documentation, https://szymonmaszke.github.io/torchlambda/#torchlambda
Project-URL: Issues, https://github.com/szymonmaszke/torchlambda/issues?q=is%3Aissue+is%3Aopen+sort%3Aupdated-desc
Keywords: aws lambda pytorch deployment minimal c++ neural network model
Platform: UNKNOWN
Classifier: Development Status :: 2 - Pre-Alpha
Classifier: Programming Language :: Python
Classifier: Programming Language :: Python :: 3
Classifier: Programming Language :: Python :: 3.6
Classifier: Programming Language :: Python :: 3.7
Classifier: Programming Language :: Python :: 3.8
Classifier: License :: OSI Approved :: MIT License
Classifier: Intended Audience :: Developers
Classifier: Operating System :: OS Independent
Classifier: Topic :: Scientific/Engineering
Classifier: Topic :: Scientific/Engineering :: Artificial Intelligence
Requires-Python: >=3.6
Requires-Dist: PyYAML (>=5.3)
Requires-Dist: Cerberus (>=1.3.2)
